{
    "department_name": "Classical Humanities",
    "department_code": "CL_HUM",
    "courses": [
        {
            "name": "Greek and Latin in English",
            "number": "1050",
            "description": "A survey of the influence of Greek and Latin upon English literary, scientific, technical, legal and medical vocabulary.  Emphasis is upon building competency with complex English words while studying the cultural influence of the classical languages on modern vocabulary.",
            "prerequisites": "None Listed",
            "hours": "3",
            "recommendation": "None Listed",
            "connections": "None Listed"
        },
        {
            "name": "Classical Mythology",
            "number": "1060",
            "description": "Myths of Greece and Rome in literature and art.",
            "prerequisites": "None Listed",
            "hours": "3",
            "recommendation": "None Listed",
            "connections": "None Listed"
        },
        {
            "name": "Classical Mythology - Honors",
            "number": "1060H",
            "description": "Myths of Greece and Rome in literature and art.",
            "prerequisites": "Honors eligibility required",
            "hours": "3",
            "recommendation": "None Listed",
            "connections": "None Listed"
        },
        {
            "name": "Classical Mythology - Honors/Writing Intensive",
            "number": "1060HW",
            "description": "Myths of Greece and Rome in literature and art.",
            "prerequisites": "Honors eligibility required",
            "hours": "3",
            "recommendation": "None Listed",
            "connections": "None Listed"
        },
        {
            "name": "Classical Mythology - Writing Intensive",
            "number": "1060W",
            "description": "Myths of Greece and Rome in literature and art.",
            "prerequisites": "None Listed",
            "hours": "3",
            "recommendation": "None Listed",
            "connections": "None Listed"
        },
        {
            "name": "Topics in Classical Humanities",
            "number": "2005",
            "description": "Organized study of selected topics. Subjects and earnable credit may vary from semester to semester.",
            "prerequisites": "None Listed",
            "hours": "1-99",
            "recommendation": "None Listed",
            "connections": "None Listed"
        },
        {
            "name": "Greek Culture",
            "number": "2100",
            "description": "Survey of Greek life and thought. Principal developments in literature, the arts, politics, religion and philosophy, and their influence on Western civilization.",
            "prerequisites": "None Listed",
            "hours": "3",
            "recommendation": "None Listed",
            "connections": "None Listed"
        },
        {
            "name": "Greek Culture - Honors",
            "number": "2100H",
            "description": "Survey of Greek life and thought. Principal developments in literature, the arts, politics, religion and philosophy, and their influence on Western civilization.",
            "prerequisites": "Honors eligibility required",
            "hours": "3",
            "recommendation": "None Listed",
            "connections": "None Listed"
        },
        {
            "name": "Roman Culture",
            "number": "2200",
            "description": "Survey of Roman life and thought. Principal developments in literature, the arts, politics, religion, philosophy, and private life, and their influence on Western Civilization.",
            "prerequisites": "None Listed",
            "hours": "3",
            "recommendation": "None Listed",
            "connections": "None Listed"
        },
        {
            "name": "Greek Classics in Translation",
            "number": "2300",
            "description": "Reading in translation and critical study of the most important literary works of the ancient Greek World.",
            "prerequisites": "None Listed",
            "hours": "3",
            "recommendation": "None Listed",
            "connections": "None Listed"
        },
        {
            "name": "Greek Classics in Translation",
            "number": "2300H",
            "description": "Reading in translation and critical study of the most important literary works of the ancient Greek world.",
            "prerequisites": "Honors eligibility required",
            "hours": "3",
            "recommendation": "None Listed",
            "connections": "None Listed"
        },
        {
            "name": "Roman Classics in Translation",
            "number": "2400",
            "description": "Reading in translation and critical study of the most important literary works of the ancient Roman world.",
            "prerequisites": "None Listed",
            "hours": "3",
            "recommendation": "None Listed",
            "connections": "None Listed"
        },
        {
            "name": "The Origins of Music in the Ancient World",
            "number": "2500",
            "description": "Explores the use of music in the earliest historical societies, from the earliest evidence up to the fall of the Roman empire. Topics will include the history of musical instruments, the earliest scores, the development of music theory, the origins of melody, rhythm, and harmony, and the relationship between music, politics, and religion. Graded on A-F basis only.",
            "prerequisites": "None Listed",
            "hours": "3",
            "recommendation": "CL_HUM 1060; CL_HUM 2100; CL_HUM 2200",
            "connections": "None Listed"
        },
        {
            "name": "Service Learning in Classical Studies",
            "number": "2940",
            "description": "Students provide enrichment programming on the Ancient World at various Columbia Public School sites. Participants must be Classical Studies majors or minors. Graded on A/F basis only. Does not meet Arts and Science general education requirements.",
            "prerequisites": "instructor's consent required",
            "hours": "1",
            "recommendation": "None Listed",
            "connections": "None Listed"
        },
        {
            "name": "Foreigners and Dangerous Women in Greek and Latin Literature",
            "number": "3000",
            "description": "(same as PEA_ST 3130). The study of how Greek and Roman writers depicted and reacted to other races and cultures, compared them with their own, and thereby revealed their own values and prejudices.",
            "prerequisites": "None Listed",
            "hours": "3",
            "recommendation": "CL_HUM 1060",
            "connections": "None Listed"
        },
        {
            "name": "Foreigners and Dangerous Women in Greek and Latin Literature - Honors",
            "number": "3000H",
            "description": "(same as PEA_ST 3130). The study of how Greek and Roman writers depicted and reacted to other races and cultures, compared them with their own, and thereby revealed their own values and prejudices.",
            "prerequisites": "Honors eligibility required",
            "hours": "3",
            "recommendation": "CL_HUM 1060",
            "connections": "None Listed"
        },
        {
            "name": "Foreigners and Dangerous Women in Greek and Latin Literature - Writing Intensive",
            "number": "3000W",
            "description": "(same as PEA_ST 3130). The study of how Greek and Roman writers depicted and reacted to other races and cultures, compared them with their own, and thereby revealed their own values and prejudices.",
            "prerequisites": "None Listed",
            "hours": "3",
            "recommendation": "CL_HUM 1060",
            "connections": "None Listed"
        },
        {
            "name": "Topics in Classical Humanities",
            "number": "3005",
            "description": "Organized study of selected topics. Subjects and earnable credit may vary from semester to semester.",
            "prerequisites": "None Listed",
            "hours": "1-99Recommended: CL_HUM 1060",
            "recommendation": "None Listed",
            "connections": "None Listed"
        },
        {
            "name": "Topics in Classical Humanities - Honors",
            "number": "3005H",
            "description": "Organized study of selected topics. Subjects and earnable credit may vary from semester to semester.",
            "prerequisites": "Honors eligibility required",
            "hours": "1-99",
            "recommendation": "CL_HUM 1060",
            "connections": "None Listed"
        },
        {
            "name": "Topics in Classical Humanities - Writing Intensive",
            "number": "3005W",
            "description": "Organized study of selected topics. Subjects and earnable credit may vary from semester to semester.",
            "prerequisites": "None Listed",
            "hours": "1-99Recommended: CL_HUM 1060",
            "recommendation": "None Listed",
            "connections": "None Listed"
        },
        {
            "name": "Ancient Western Philosophy",
            "number": "3025",
            "description": "(same as PHIL 3000). Philosophical thought on nature, knowledge, the gods, human life and society, from Thales to Augustine. Emphasis on Plato and Aristotle. The relevance of the ancients to contemporary life.",
            "prerequisites": "None Listed",
            "hours": "3",
            "recommendation": "CL_HUM 1060",
            "connections": "None Listed"
        },
        {
            "name": "Philosophy Before Socrates",
            "number": "3050",
            "description": "A study of the origin of philosophical thinking in the Ancient Greek world.  Topics to be explored include the nature of reality and our knowledge of it, the structure and constituents of the cosmos, human excellence and its relation to morality, political power, and happiness.",
            "prerequisites": "None Listed",
            "hours": "3",
            "recommendation": "CL_HUM 1060",
            "connections": "None Listed"
        },
        {
            "name": "Philosophy Before Socrates - Honors",
            "number": "3050H",
            "description": "A study of the origin of philosophical thinking in the Ancient Greek world.  Topics to be explored include the nature of reality and our knowledge of it, the structure and constituents of the cosmos, human excellence and its relation to morality, political power, and happiness.",
            "prerequisites": "Honors eligibility required",
            "hours": "3",
            "recommendation": "CL_HUM 1060",
            "connections": "None Listed"
        },
        {
            "name": "The Age of Pericles",
            "number": "3100",
            "description": "A study of the literature and culture of the 5th and early 4th centuries B.C. in Athens. Authors will include Thucydides, Herodotus, Xenophon, Plato, Aristotle, the tragedians and Aristophanes.",
            "prerequisites": "None Listed",
            "hours": "3",
            "recommendation": "CL_HUM 1060",
            "connections": "None Listed"
        },
        {
            "name": "The Age of Pericles - Honors",
            "number": "3100H",
            "description": "A study of the literature and culture of the 5th and early 4th centuries B.C. in Athens. Authors will include Thucydides, Herodotus, Xenophon, Plato, Aristotle, the tragedians and Aristophanes.",
            "prerequisites": "Honors eligibility required",
            "hours": "3",
            "recommendation": "CL_HUM 1060",
            "connections": "None Listed"
        },
        {
            "name": "The Age of Augustus",
            "number": "3150",
            "description": "Study of the literature of the Age of Augustus; Vergil, Ovid, Horace, Livy, and Propertius.",
            "prerequisites": "None Listed",
            "hours": "3",
            "recommendation": "CL_HUM 1060",
            "connections": "None Listed"
        },
        {
            "name": "The Age of Augustus - Honors",
            "number": "3150H",
            "description": "Study of the literature of the Age of Augustus; Vergil, Ovid, Horace, Livy, and Propertius.",
            "prerequisites": "Honors eligibility required",
            "hours": "3",
            "recommendation": "CL_HUM 1060",
            "connections": "None Listed"
        },
        {
            "name": "Power and Oratory in Ancient Greece",
            "number": "3200",
            "description": "Concentrates on the rise of oratory in Greece and how oratory was exploited for political ends. Special attention will be paid to the Athenian Democracy in the fifth and fourth centuries BC.",
            "prerequisites": "None Listed",
            "hours": "3",
            "recommendation": "CL_HUM 1060",
            "connections": "None Listed"
        },
        {
            "name": "Power and Oratory in Ancient Greece - Honors",
            "number": "3200H",
            "description": "Concentrates on the rise of oratory in Greece and how oratory was exploited for political ends. Special attention will be paid to the Athenian Democracy in the fifth and fourth centuries BC.",
            "prerequisites": "Honors eligibility required",
            "hours": "3",
            "recommendation": "CL_HUM 1060",
            "connections": "None Listed"
        },
        {
            "name": "Roman Comedy, Wit and Humor",
            "number": "3225",
            "description": "Study of works illustrating the comedy, wit and humor of the Romans: readings in comedies of Plautus and Terence, Catullus, Ovid's Metamorphoses,  Petronius' Satyricon, Martial, Juvenal and Macrobius.",
            "prerequisites": "None Listed",
            "hours": "3",
            "recommendation": "CL_HUM 1060",
            "connections": "None Listed"
        },
        {
            "name": "Greek and Roman Epic",
            "number": "3250",
            "description": "A study of the major representatives of the ancient epic genre. Readings will include Homer's Iliad and Odyssey, Apollonius' Argonautica, Vergil's Aeneid.",
            "prerequisites": "None Listed",
            "hours": "3",
            "recommendation": "CL_HUM 1060",
            "connections": "None Listed"
        },
        {
            "name": "Greek and Roman Epic - Honors",
            "number": "3250H",
            "description": "A study of the major representatives of the ancient epic genre. Readings will include Homer's Iliad and Odyssey, Apollonius' Argonautica, Vergil's Aeneid.",
            "prerequisites": "Honors eligibility required",
            "hours": "3",
            "recommendation": "CL_HUM 1060",
            "connections": "None Listed"
        },
        {
            "name": "Greek Drama",
            "number": "3300",
            "description": "Reading and interpretation of Greek tragedies and comedies in translation.",
            "prerequisites": "None Listed",
            "hours": "3",
            "recommendation": "CL_HUM 1060",
            "connections": "None Listed"
        },
        {
            "name": "Greek Drama - Honors",
            "number": "3300H",
            "description": "Reading and interpretation of Greek tragedies and comedies in translation.",
            "prerequisites": "Honors eligibility required",
            "hours": "3",
            "recommendation": "CL_HUM 1060",
            "connections": "None Listed"
        },
        {
            "name": "Advanced Mythology",
            "number": "3350",
            "description": "Interpretation of selected classical myths and their influence on later literature and art.",
            "prerequisites": "None Listed",
            "hours": "3",
            "recommendation": "CL_HUM 1060",
            "connections": "None Listed"
        },
        {
            "name": "Advanced Mythology - Honors",
            "number": "3350H",
            "description": "Interpretation of selected classical myths and their influence on later literature and art.",
            "prerequisites": "Honors eligibility required",
            "hours": "3",
            "recommendation": "CL_HUM 1060",
            "connections": "None Listed"
        },
        {
            "name": "Murder and Mayhem: Images of Justice in Classical Antiquity",
            "number": "3400",
            "description": "Ideas of justice from Homer through the early Roman Empire; personal vengeance, law courts and trials, philosophical attitudes, women and courts, techniques of persuasion.",
            "prerequisites": "None Listed",
            "hours": "3",
            "recommendation": "CL_HUM 1060",
            "connections": "None Listed"
        },
        {
            "name": "Murder & Mayhem: Images of Justice in Classical Antiquity - Honors",
            "number": "3400H",
            "description": "Ideas of justice from Homer through the early Roman Empire; personal vengeance, law courts and trials, philosophical attitudes, women and courts, techniques of persuasion.",
            "prerequisites": "Honors eligibility required",
            "hours": "3",
            "recommendation": "CL_HUM 1060",
            "connections": "None Listed"
        },
        {
            "name": "Murder and Mayhem: Images of Justice in Classical Antiquity - Writing Intensive",
            "number": "3400W",
            "description": "Ideas of justice from Homer through the early Roman Empire; personal vengeance, law courts and trials, philosophical attitudes, women and courts, techniques of persuasion.",
            "prerequisites": "None Listed",
            "hours": "3",
            "recommendation": "CL_HUM 1060",
            "connections": "None Listed"
        },
        {
            "name": "Greek and Roman Characters and Ideals",
            "number": "3450",
            "description": "Study of selected types of characters admired and imitated or hated and rejected in classical antiquity; heroes, philosophers, women.",
            "prerequisites": "None Listed",
            "hours": "3",
            "recommendation": "CL_HUM 1060",
            "connections": "None Listed"
        },
        {
            "name": "Greek and Roman Characters and Ideals - Honors",
            "number": "3450H",
            "description": "Study of selected types of characters admired and imitated or hated and rejected in classical antiquity; heroes, philosophers, women.",
            "prerequisites": "Honors eligibility required",
            "hours": "3",
            "recommendation": "CL_HUM 1060",
            "connections": "None Listed"
        },
        {
            "name": "War and Democracy in Late 5th c. BCE Athens",
            "number": "3550",
            "description": "(same as PEA_ST 3550).  Explores the discourse on war and peace in Athenian texts and art that survives from the last quarter of the 5th century B.C.E.  This was a period of relentless warfare: the Athenians were fighting the Spartans, Sparta's allies, unaligned cities and several of their own subject states.",
            "prerequisites": "None Listed",
            "hours": "3",
            "recommendation": "CL_HUM 1060",
            "connections": "None Listed"
        },
        {
            "name": "The Ancient Novel",
            "number": "3600",
            "description": "Reading and analysis of Greek and Latin prose fiction: ideal and comic romance, fantasy, romantic biography; Hellenistic background.",
            "prerequisites": "None Listed",
            "hours": "3",
            "recommendation": "CL_HUM 1060",
            "connections": "None Listed"
        },
        {
            "name": "The Ancient Novel - Honors",
            "number": "3600H",
            "description": "Reading and analysis of Greek and Latin prose fiction: ideal and comic romance, fantasy, romantic biography; Hellenistic background.",
            "prerequisites": "Honors eligibility required",
            "hours": "3",
            "recommendation": "CL_HUM 1060",
            "connections": "None Listed"
        },
        {
            "name": "Paganism and Christianity",
            "number": "3650",
            "description": "A study of the transition from Paganism to Christianity in the Roman Empire, as seen by observers contemporary with the events.",
            "prerequisites": "None Listed",
            "hours": "3",
            "recommendation": "CL_HUM 1060",
            "connections": "None Listed"
        },
        {
            "name": "Paganism and Christianity - Honors",
            "number": "3650H",
            "description": "A study of the transition from Paganism to Christianity in the Roman Empire, as seen by observers contemporary with the events.",
            "prerequisites": "Honors eligibility required",
            "hours": "3",
            "recommendation": "CL_HUM 1060",
            "connections": "None Listed"
        },
        {
            "name": "Paganism and Christianity - Writing Intensive",
            "number": "3650W",
            "description": "A study of the transition from Paganism to Christianity in the Roman Empire, as seen by observers contemporary with the events.",
            "prerequisites": "None Listed",
            "hours": "3",
            "recommendation": "CL_HUM 1060",
            "connections": "None Listed"
        },
        {
            "name": "Women in the Ancient World",
            "number": "3700",
            "description": "Using classical literary texts as the central focus this course examines the role of women: the conflict inherent in their obligations and their identity in the context of these obligations.",
            "prerequisites": "None Listed",
            "hours": "3",
            "recommendation": "CL_HUM 1060",
            "connections": "None Listed"
        },
        {
            "name": "Women in the Ancient World - Honors",
            "number": "3700H",
            "description": "Using classical literary texts as the central focus this course examines the role of women: the conflict inherent in their obligations and their identity in the context of these obligations.",
            "prerequisites": "Honors eligibility required",
            "hours": "3",
            "recommendation": "CL_HUM 1060",
            "connections": "None Listed"
        },
        {
            "name": "Classics in a Cross-Cultural Context",
            "number": "3750",
            "description": "The goal of this course is to place classical literature in a multicultural context by studying Greek and Latin literary texts alongside verbal art from non-European as well as European cultures.",
            "prerequisites": "None Listed",
            "hours": "3",
            "recommendation": "CL_HUM 1060",
            "connections": "None Listed"
        },
        {
            "name": "Classics in a Cross-Cultural Context - Honors",
            "number": "3750H",
            "description": "The goal of this course is to place classical literature in a multicultural context by studying Greek and Latin literary texts alongside verbal art from non-European as well as European cultures.",
            "prerequisites": "Honors eligibility required",
            "hours": "3",
            "recommendation": "CL_HUM 1060",
            "connections": "None Listed"
        },
        {
            "name": "The Ancient World on Film",
            "number": "3775",
            "description": "(same as AR_H_A 3775 and FILM_S 3775).  This course explores how classical antiquity has been represented in twentieth and twenty-first-century film, with particular emphasis on the ways in which ancient narratives and iconography have been appropriated by filmmakers to address contemporary cultural issues.",
            "prerequisites": "None Listed",
            "hours": "3",
            "recommendation": "CL_HUM 1060",
            "connections": "None Listed"
        },
        {
            "name": "The Ancient World on Film - Writing Intensive",
            "number": "3775W",
            "description": "(same as AR_H_A 3775 and FILM_S 3775).  This course explores how classical antiquity has been represented in twentieth and twenty-first-century film, with particular emphasis on the ways in which ancient narratives and iconography have been appropriated by filmmakers to address contemporary cultural issues.",
            "prerequisites": "None Listed",
            "hours": "3",
            "recommendation": "CL_HUM 1060",
            "connections": "None Listed"
        },
        {
            "name": "Sports and Spectacles in Greco-Roman Antiquity",
            "number": "3800",
            "description": "Investigates athletic display in ancient Greek and Roman culture, from its earliest representations in Greek literature to the massive spectacles of the Roman empire, with an emphasis on the intersections between sport and spectacle and other areas of ancient cultural life.",
            "prerequisites": "None Listed",
            "hours": "3",
            "recommendation": "CL_HUM 1060",
            "connections": "None Listed"
        },
        {
            "name": "Topics in Classical Humanities",
            "number": "4005",
            "description": "Subjects and earnable credit may vary from semester to semester.",
            "prerequisites": "None Listed",
            "hours": "1-99Recommended: CL_HUM 1060 and junior standing",
            "recommendation": "None Listed",
            "connections": "None Listed"
        },
        {
            "name": "Greece: From the Bronze Age to the Byzantine Empire",
            "number": "4100",
            "description": "Study abroad in Greece, in conjunction with the MU International Center. Immersion in the physical and intellectual heritage of ancient Greece; emphasis on cross-disciplinary, on-site learning and the intersections among ancient, Byzantine, and modern Greece. Application required. Graded on A/F basis only.",
            "prerequisites": "None Listed",
            "hours": "6",
            "recommendation": "CL_HUM 1060",
            "connections": "None Listed"
        },
        {
            "name": "Greece: From the Bronze Age to the Byzantine Empire - Honors",
            "number": "4100H",
            "description": "Study abroad in Greece, in conjunction with the MU International Center. Immersion in the physical and intellectual heritage of ancient Greece; emphasis on cross-disciplinary, on-site learning and the intersections among ancient, Byzantine, and modern Greece. Participants chosen by instructor. Graded on A/F basis only. Application required.",
            "prerequisites": "Honors eligibility required",
            "hours": "6",
            "recommendation": "CL_HUM 1060",
            "connections": "None Listed"
        },
        {
            "name": "Greek and Roman Religion",
            "number": "4500",
            "description": "(same as REL_ST 4500). Survey of religious development among the Greeks and Romans.",
            "prerequisites": "None Listed",
            "hours": "3",
            "recommendation": "CL_HUM 1060 and junior standing",
            "connections": "None Listed"
        },
        {
            "name": "Greek and Roman Religion - Honors",
            "number": "4500H",
            "description": "(same as REL_ST 4500). Survey of religious development among the Greeks and Romans.",
            "prerequisites": "Honors eligibility required",
            "hours": "3",
            "recommendation": "CL_HUM 1060 and junior standing",
            "connections": "None Listed"
        },
        {
            "name": "Literature and Culture of the Hellenistic Age",
            "number": "4550",
            "description": "(cross-leveled with CL_HUM 7550). A survey of the literature and culture of the Hellenistic Age.",
            "prerequisites": "None Listed",
            "hours": "3",
            "recommendation": "CL_HUM 1060 and junior standing",
            "connections": "None Listed"
        },
        {
            "name": "Literature and Culture of the Hellenistic Age - Honors",
            "number": "4550H",
            "description": "A survey of the literature and culture of the Hellenistic Age.",
            "prerequisites": "Honors eligibility required",
            "hours": "3",
            "recommendation": "CL_HUM 1060 and junior standing",
            "connections": "None Listed"
        },
        {
            "name": "The Classical Tradition",
            "number": "4600",
            "description": "Selected studies in continuity and influence of Greek and Roman culture on Middle Ages, Renaissance, and modern times.",
            "prerequisites": "None Listed",
            "hours": "3",
            "recommendation": "CL_HUM 1060 and junior standing",
            "connections": "None Listed"
        },
        {
            "name": "The Classical Tradition - Honors",
            "number": "4600H",
            "description": "Selected studies in continuity and influence of Greek and Roman culture on Middle Ages, Renaissance, and modern times.",
            "prerequisites": "Honors eligibility required",
            "hours": "3",
            "recommendation": "CL_HUM 1060 and junior standing",
            "connections": "None Listed"
        },
        {
            "name": "The Classical Tradition - Honors/Writing Intensive",
            "number": "4600HW",
            "description": "Selected studies in continuity and influence of Greek and Roman culture on Middle Ages, Renaissance, and modern times.",
            "prerequisites": "None Listed",
            "hours": "3",
            "recommendation": "CL_HUM 1060 and junior standing",
            "connections": "None Listed"
        },
        {
            "name": "The Classical Tradition - Writing Intensive",
            "number": "4600W",
            "description": "Selected studies in continuity and influence of Greek and Roman culture on Middle Ages, Renaissance, and modern times.",
            "prerequisites": "None Listed",
            "hours": "3",
            "recommendation": "CL_HUM 1060 and junior standing",
            "connections": "None Listed"
        },
        {
            "name": "The World of Late Antiquity",
            "number": "4650",
            "description": "(cross-leveled with CL_HUM 7650). A survey of the literature, culture, and history of the late Roman and early Byzantine periods. Attention to Christianity's development and the transformation of the classical heritage.",
            "prerequisites": "None Listed",
            "hours": "3",
            "recommendation": "CL_HUM 1060 and junior standing",
            "connections": "None Listed"
        },
        {
            "name": "The World of Late Antiquity - Honors",
            "number": "4650H",
            "description": "A survey of the literature, culture, and history of the late Roman and early Byzantine periods. Attention to Christianity's development and the transformation of the classical heritage.",
            "prerequisites": "Honors eligibility required",
            "hours": "3",
            "recommendation": "CL_HUM 1060 and junior standing",
            "connections": "None Listed"
        },
        {
            "name": "Oral Tradition",
            "number": "4770",
            "description": "(same as ENGLSH 4770). Study of verbal art from living oral traditions (e.g. Native American and African American) and important literary works with roots in oral tradition (e.g. the Bible, the Iliad and Odyssey, and Beowulf).",
            "prerequisites": "None Listed",
            "hours": "3",
            "recommendation": "CL_HUM 1060 and junior standing",
            "connections": "None Listed"
        },
        {
            "name": "Oral Tradition - Honors",
            "number": "4770H",
            "description": "(same as ENGLSH 4770). Study of verbal art from living oral traditions (e.g. Native American and African American) and important literary works with roots in oral tradition (e.g. the Bible, the Iliad and Odyssey, and Beowulf).",
            "prerequisites": "Honors eligibility required",
            "hours": "3",
            "recommendation": "CL_HUM 1060 and junior standing",
            "connections": "None Listed"
        },
        {
            "name": "Political Thought in Classical and Christian Antiquity",
            "number": "4800",
            "description": "(same as POL_SC 4800).  Reading and discussion of Greek, Roman, and Early Christian treatises on politics and political life. Survey of the political institutions and procedures of the Greek city states and Roman Republic and Empire. Examination of contemporary Christian responses and adaptations.",
            "prerequisites": "None Listed",
            "hours": "3",
            "recommendation": "CL_HUM 1060 and junior standing",
            "connections": "None Listed"
        },
        {
            "name": "Capstone in Classical Humanities",
            "number": "4970",
            "description": "Culminating course in the study of Greek and Roman literature and Classical Culture.  Required for Classical Humanities majors in first term of senior year.",
            "prerequisites": "instructor's consent",
            "hours": "3",
            "recommendation": "None Listed",
            "connections": "None Listed"
        },
        {
            "name": "Capstone in Classical Humanities- Honors",
            "number": "4970H",
            "description": "Culminating course in the study of Greek and Roman literature and Classical Culture.  Required for Classical Humanities majors in first term of senior year.",
            "prerequisites": "instructor's consent; Honors eligibility required",
            "hours": "3",
            "recommendation": "for Classical Humanities double-majors",
            "connections": "None Listed"
        },
        {
            "name": "Topics in Classical Humanities",
            "number": "7005",
            "description": "Subjects and earnable credit may vary from semester to semester.",
            "prerequisites": "any Classical Humanities 3000 level course or instructor's consent",
            "hours": "1-99",
            "recommendation": "None Listed",
            "connections": "None Listed"
        },
        {
            "name": "Literature and Culture of the Hellenistic Age",
            "number": "7550",
            "description": "(cross-leveled with CL_HUM  7550). A survey of the literature and culture of the Hellenistic Age. Graded on A-F basis only.",
            "prerequisites": "None Listed",
            "hours": "3",
            "recommendation": "None Listed",
            "connections": "None Listed"
        },
        {
            "name": "The World of Late Antiquity",
            "number": "7650",
            "description": "(cross-leveled with CL_HUM 4650). A survey of the literature, culture, and history of the late Roman and early Byzantine periods. Attention to Christianity's development and the transformation of the classical heritage.",
            "prerequisites": "None Listed",
            "hours": "3",
            "recommendation": "None Listed",
            "connections": "None Listed"
        }
    ]
}